{"addEntity":"mutation m{addEntity(entity:{entityType:\"Müşteriler\",name:\"Tuncay Ünver - 5331936806\"}){name}}","updateEntityCustomData":["mutation m {\n  updateEntityCustomData(entityTypeName: \"Müşteriler\", entityName: \"Tuncay Ünver - 5331936806\", name: \"Adres\", value: \"Orman Genel Md. Tesisleri- Apt. No: 47 - Beştepe Yenimahalle - Açıklama: - ÇATAL-BIÇAK GÖNDERMEYİN Nakit\"){name}\n}","mutation m {\n  updateEntityCustomData(entityTypeName: \"Müşteriler\", entityName: \"Tuncay Ünver - 5331936806\", name: \"Telefon\", value: \"5331936806\"){name}\n}","mutation m {\n  updateEntityCustomData(entityTypeName: \"Müşteriler\", entityName: \"Tuncay Ünver - 5331936806\", name: \"Ad Soyad\", value: \"Tuncay Ünver\"){name}\n}"],"registerTerminal":"mutation m {registerTerminal(user: \"Yemek Sepeti\", ticketType: \"Paket Servis\", terminal: \"Sunucu\", department: \"Restoran\")}","createTerminalTicket":"mutation m {createTerminalTicket(terminalId:\"{terminalId}\"){uid}}","updateTerminalTicket":"mutation m {  updateTerminalTicket(terminalId: \"{terminalId}\", note: \"- ÇATAL-BIÇAK GÖNDERMEYİN Nakit\", states: [{\"stateName\":\"Ödeme Şekli\",\"state\":\"Nakit\"},{\"stateName\":\"Kaynak\",\"state\":\"Yemek Sepeti\"}], tags: [{\"tagName\":\"Ödeme Şekli\",\"tag\":\"Nakit\"},{\"tagName\":\"ID\",\"tag\":\"63fb3a4f7047d10744cb90dd\"}]){id}}","addProduct":["mutation m {\n                addProduct(name: \"Cajun Mix Menü\", groupCode: \"Entegrasyon\", portions: {name: \"Normal\", price:1}) {\n                  id\n                }\n              }"],"getProduct":[{"name":"Cajun Mix Menü"}],"addOrderToTerminalTicketWithProduct":["mutation m {addOrderToTerminalTicket(terminalId:\"{terminalId}\",productId:{productId},price:220,quantity:1,portion:\"Normal\",orderTags:\"Ürün Etiketi=Cajun Burger:Patates Kızartması,Ürün Etiketi=Cajun Burger:Soğan Halkası,Ürün Etiketi=Sprite 33 cl.,Ürün Etiketi=Coca-Cola 33 cl.\"){orders{uid}}}"],"addCalculationToTerminalTicket":"mutation m { addCalculationToTerminalTicket(terminalId:\"{terminalId}\",calculationName:\"Joker İskonto\",amount:44){id}}","changeEntityOfTerminalTicket":"mutation m {changeEntityOfTerminalTicket (terminalId:\"{terminalId}\",type:\"Müşteriler\",name:\"Tuncay Ünver - 5331936806\"){uid}}","closeTerminalTicket":"mutation m {closeTerminalTicket(terminalId:\"{terminalId}\")}","getTerminalTickets":"mutation m {getTerminalTickets (terminalId:\"{terminalId}\"){id,uid}}","unregisterTerminal":"mutation m {unregisterTerminal(terminalId:\"{terminalId}\")}","postTicketRefreshMessage":"mutation m {\n                        postTicketRefreshMessage(id: 0) {\n                          id\n                        }\n                      }","postBroadcastMessage":"mutation m { postBroadcastMessage(message: \"ENT-YeniSiparis-ys\") {\n                              message\n                            }\n                          }"}